fff_ir_lint/__init__.py
fff_ir_lint/lint.py
fff_ir_lint/lint_collector_format.py
fff_ir_lint/lint_github_2_format.py
fff_ir_lint/lint_github_format.py
fff_ir_lint/lint_simple_format.py
fff_ir_lint-0.0.1.dist-info/METADATA
fff_ir_lint-0.0.1.dist-info/WHEEL
fff_ir_lint-0.0.1.dist-info/RECORD
