Metadata-Version: 2.1
Name: fff_ir_lint
Version: 0.0.1
Summary: .ir Linter for FFF
Project-URL: Homepage, https://github.com/darmiel/fff-ir-lint
Author-email: darmiel <asdf@qwer.tz>
Classifier: License :: OSI Approved :: MIT License
Classifier: Operating System :: OS Independent
Classifier: Programming Language :: Python :: 3
Requires-Python: >=3.7
